{
  "formatVersion": 1,
  "database": {
    "version": 12,
    "identityHash": "10b9f219244787004f967a03532abc21",
    "entities": [
      {
        "tableName": "category_table",
        "createSql": "CREATE TABLE IF NOT EXISTS `${TABLE_NAME}` (`ofUser` TEXT NOT NULL, `title` TEXT NOT NULL, `aggregate` REAL NOT NULL, `budget` REAL NOT NULL, `icon` INTEGER NOT NULL, `isBackedUp` INTEGER NOT NULL DEFAULT 0, PRIMARY KEY(`ofUser`, `title`))",
        "fields": [
          {
            "fieldPath": "ofUser",
            "columnName": "ofUser",
            "affinity": "TEXT",
            "notNull": true
          },
          {
            "fieldPath": "title",
            "columnName": "title",
            "affinity": "TEXT",
            "notNull": true
          },
          {
            "fieldPath": "aggregate",
            "columnName": "aggregate",
            "affinity": "REAL",
            "notNull": true
          },
          {
            "fieldPath": "budget",
            "columnName": "budget",
            "affinity": "REAL",
            "notNull": true
          },
          {
            "fieldPath": "icon",
            "columnName": "icon",
            "affinity": "INTEGER",
            "notNull": true
          },
          {
            "fieldPath": "isBackedUp",
            "columnName": "isBackedUp",
            "affinity": "INTEGER",
            "notNull": true,
            "defaultValue": "0"
          }
        ],
        "primaryKey": {
          "columnNames": [
            "ofUser",
            "title"
          ],
          "autoGenerate": false
        },
        "indices": [],
        "foreignKeys": []
      },
      {
        "tableName": "expense_table",
        "createSql": "CREATE TABLE IF NOT EXISTS `${TABLE_NAME}` (`ofUser` TEXT NOT NULL, `id` INTEGER PRIMARY KEY AUTOINCREMENT NOT NULL, `title` TEXT NOT NULL, `amount` REAL NOT NULL, `ofCategory` TEXT NOT NULL, `createdOn` TEXT NOT NULL, `backedUp` INTEGER NOT NULL DEFAULT 0)",
        "fields": [
          {
            "fieldPath": "ofUser",
            "columnName": "ofUser",
            "affinity": "TEXT",
            "notNull": true
          },
          {
            "fieldPath": "id",
            "columnName": "id",
            "affinity": "INTEGER",
            "notNull": true
          },
          {
            "fieldPath": "title",
            "columnName": "title",
            "affinity": "TEXT",
            "notNull": true
          },
          {
            "fieldPath": "amount",
            "columnName": "amount",
            "affinity": "REAL",
            "notNull": true
          },
          {
            "fieldPath": "ofCategory",
            "columnName": "ofCategory",
            "affinity": "TEXT",
            "notNull": true
          },
          {
            "fieldPath": "createdOn",
            "columnName": "createdOn",
            "affinity": "TEXT",
            "notNull": true
          },
          {
            "fieldPath": "backedUp",
            "columnName": "backedUp",
            "affinity": "INTEGER",
            "notNull": true,
            "defaultValue": "0"
          }
        ],
        "primaryKey": {
          "columnNames": [
            "id"
          ],
          "autoGenerate": true
        },
        "indices": [],
        "foreignKeys": []
      },
      {
        "tableName": "category_icon_table",
        "createSql": "CREATE TABLE IF NOT EXISTS `${TABLE_NAME}` (`title` TEXT NOT NULL, `icon` INTEGER NOT NULL, PRIMARY KEY(`title`))",
        "fields": [
          {
            "fieldPath": "title",
            "columnName": "title",
            "affinity": "TEXT",
            "notNull": true
          },
          {
            "fieldPath": "icon",
            "columnName": "icon",
            "affinity": "INTEGER",
            "notNull": true
          }
        ],
        "primaryKey": {
          "columnNames": [
            "title"
          ],
          "autoGenerate": false
        },
        "indices": [],
        "foreignKeys": []
      }
    ],
    "views": [],
    "setupQueries": [
      "CREATE TABLE IF NOT EXISTS room_master_table (id INTEGER PRIMARY KEY,identity_hash TEXT)",
      "INSERT OR REPLACE INTO room_master_table (id,identity_hash) VALUES(42, '10b9f219244787004f967a03532abc21')"
    ]
  }
}